<?xml version="1.0" encoding="UTF-8"?>
<language type="english">

    <expression>
        <name>MainFremeTitle</name>
        <value>Syntese</value>
    </expression>
    
    
    <expression>
        <name>FileMenu</name>
        <value>File</value>
    </expression>
    <expression>
        <name>NewMenu</name>
        <value>New</value>
    </expression>
    <expression>
        <name>OpenMenu</name>
        <value>Open</value>
    </expression>
    <expression>
        <name>CloseMenu</name>
        <value>Close</value>
    </expression>
    <expression>
        <name>CloseAllMenu</name>
        <value>Close All</value>
    </expression>
    <expression>
        <name>SaveMenu</name>
        <value>Save</value>
    </expression>
    <expression>
        <name>SaveAsMenu</name>
        <value>Save As</value>
    </expression>
    <expression>
        <name>SaveAllMenu</name>
        <value>Save All</value>
    </expression>
    <expression>
        <name>HelpMenu</name>
        <value>Help</value>
    </expression>
    <expression>
        <name>LanguageMenu</name>
        <value>Language</value>
    </expression>
    <expression>
        <name>AboutMenu</name>
        <value>About</value>
    </expression>
    
    <expression>
      <name>Wizard_CamType_title</name>
      <value>Selecting the desired type of the cam gear</value>
    </expression>
    <expression>
      <name>Wizard_CamType_rollerLevel</name>
      <value>Cam gear with roller lever</value>
    </expression>
    <expression>
      <name>Wizard_CamType_rollerCams</name>
      <value>Cam gear with roller cams</value>
    </expression>
    <expression>
      <name>Wizard_CamType_name</name>
      <value>Please enter name of project</value>
    </expression>
    
</language>